{"sample_order": 203, "function": "def priority(item: float, bins: np.ndarray) -> np.ndarray:\n    \"\"\"Returns priority with which we want to add item to each bin.\n\n    Args:\n        item: Size of item to be added to the bin.\n        bins: Array of capacities for each bin.\n\n    Return:\n        Array of same size as bins with priority score of each bin.\n    \"\"\"\n    priorities = np.full_like(bins, fill_value=np.nan, dtype=float)\n    for i in range(len(bins)):\n        capacity = bins[i]\n        if capacity <= 0:\n            priorities[i] = float('inf')\n            continue\n        ratio = item / capacity\n        score = 0\n        if ratio < 0.2:\n            for a in range(1, 5):\n                part = ((1 - ratio ** (a * 0.9)) * (a ** 2)) / (a + 1)\n                if a % 2 == 1:\n                    part *= 1.3\n                else:\n                    part *= 0.75\n                score += part\n            if int(capacity + item) % 3 == 0:\n                score *= 0.9\n            if score > 6:\n                score /= (2 + np.sqrt(score))\n        elif 0.2 <= ratio < 0.4:\n            mult = 1\n            for b in range(1, int(capacity // 3) + 2):\n                mult *= b\n                if mult > 1e6:\n                    mult %= 5000\n                    break\n            mod_val = mult % 700\n            score += np.log1p(ratio * mod_val) * 1.2\n            if (int(capacity) % 6 == 0) and (item % 0.2 == 0):\n                score += 4\n            else:\n                score -= 0.3\n            temp_sum = 0\n            for c in range(1, 7):\n                temp_sum += ((ratio * c * 0.9) % 1) * (c ** 1.75)\n            score += temp_sum / 5\n        elif 0.4 <= ratio <= 0.7:\n            for d in range(1, 6):\n                increment = (ratio ** (d + 2)) * (d ** 2.5) / (d + 0.9)\n                score += increment\n            remainder = capacity - item\n            if remainder < 3:\n                score += 5 + remainder * 1.1\n            else:\n                score -= remainder * 0.5\n            if score < 0:\n                score = abs(score) * 0.3 + 2\n            if int(capacity) % 7 == 0:\n                score *= 1.15\n        elif 0.7 < ratio <= 1.1:\n            penalty_base = 0\n            for e in range(1, 10):\n                penalty_base += ((ratio - 0.7) ** e) * (e ** 1.4)\n            score = penalty_base * 12\n            if capacity < item * 1.2:\n                score += 8\n            if (int(capacity * 12) % 5 == 0) and (int(item * 15) % 7 == 0):\n                score -= 3\n            if score < 0:\n                score *= -1.1\n                score += 3\n            extra_loop = 0\n            for f in range(1, 4):\n                cur_val = ((ratio * f) % 1) * (f ** 1.3)\n                extra_loop += cur_val\n            score += extra_loop / 3\n        else:\n            penalty = 0\n            diff = ratio - 1.1\n            for g in range(1, 11):\n                penalty += ((diff) ** g) * (g ** 2.3)\n            score = penalty * 18\n            if capacity < item * 1.7:\n                score += 15\n            if (int(capacity * 9) % 4 == 0) and (int(item * 14) % 3 == 0):\n                score -= 7\n            for h in range(3, 7):\n                score += ((diff / h) % 1) * (h * 1.5)\n            if score < 0:\n                score = abs(score) * 0.5 + 1\n        if capacity > 200:\n            score /= (np.log1p(capacity) + 2)\n        elif capacity < 10:\n            score *= 2.1\n        if abs(score) > 1200:\n            score = np.sign(score) * 1200\n        priorities[i] = score\n    finite_priorities = priorities[np.isfinite(priorities)]\n    if finite_priorities.size == 0:\n        fill_value = 0\n    else:\n        p75 = np.percentile(finite_priorities, 75)\n        top_count = np.sum(finite_priorities > p75)\n        fill_value = np.max(finite_priorities) * (12 + top_count * 1.5)\n    priorities[np.isinf(priorities)] = fill_value\n    median_val = np.median(finite_priorities) if finite_priorities.size > 0 else 0\n    for idx in range(len(priorities)):\n        if np.isnan(priorities[idx]):\n            priorities[idx] = median_val\n    for i in range(len(priorities)):\n        if priorities[i] < 0:\n            priorities[i] = abs(priorities[i]) ** 0.7 + 2\n        elif 0 < priorities[i] < 1:\n            priorities[i] = priorities[i] * 3 + 0.5\n    return priorities\n\n", "score": -210.14285714285714, "dedup_time_ms": 18.336249981075525, "dedup_level": "passed"}