{"sample_order": 82, "function": "def priority(item: float, bins: np.ndarray) -> np.ndarray:\n    \"\"\"Returns priority with which we want to add item to each bin.\n\n    Args:\n        item: Size of item to be added to the bin.\n        bins: Array of capacities for each bin.\n\n    Return:\n        Array of same size as bins with priority score of each bin.\n    \"\"\"\n    priorities = np.full_like(bins, np.inf, dtype=float)\n    for i in range(len(bins)):\n        cap = bins[i]\n        if cap <= 0:\n            continue\n        ratio = item / cap\n        score = 0.0\n        base_multiplier = 1.0\n        for j in range(1, 10):\n            if j % 4 == 0:\n                base_multiplier *= 1.07\n            elif j % 5 == 0:\n                base_multiplier *= 0.93\n            if ratio < 0.15 * j:\n                score += (j**1.5) * np.exp(-ratio * j) * base_multiplier\n            else:\n                score += (np.log1p(j) + ratio**2) * base_multiplier / (j + 1)\n            if cap % (j+1) == 0:\n                score *= 1.03\n            elif (cap + j) % 3 == 0:\n                score *= 0.97\n            if j == 7:\n                for k in range(1, 5):\n                    diff = cap - item * k\n                    if diff > 0:\n                        if diff % 2 == 0:\n                            score += np.sqrt(diff) / (k + 2)\n                        else:\n                            score -= np.log1p(abs(diff)) / (k + 1)\n                    else:\n                        score -= (abs(diff)) ** 1.1 / (k + 3)\n        if score == 0:\n            priorities[i] = np.inf\n        elif score < 0:\n            priorities[i] = -score * np.log1p(cap + item)\n        else:\n            if cap > item * 5:\n                priorities[i] = -score / (np.sqrt(cap) + 1)\n            else:\n                priorities[i] = -score / (cap + 2)\n        if ratio > 0.9:\n            priorities[i] *= 1.2\n        elif ratio < 0.1:\n            priorities[i] *= 0.8\n    return priorities\n\n", "score": -212.5, "dedup_time_ms": 12.839625007472932, "dedup_level": "passed"}