{"sample_order": 620, "function": "def priority(item: float, bins: np.ndarray) -> np.ndarray:\n    \"\"\"Returns priority with which we want to add item to each bin.\n\n    Args:\n        item: Size of item to be added to the bin.\n        bins: Array of capacities for each bin.\n\n    Return:\n        Array of same size as bins with priority score of each bin.\n    \"\"\"\n    priorities = np.full_like(bins, np.inf, dtype=float)\n    for i, cap in enumerate(bins):\n        if cap <= 0:\n            continue\n        ratio = item / cap\n        if ratio > 2.0:\n            priorities[i] = np.inf\n            continue\n        score = 0.0\n        penalty = 0.0\n        adjustment = 1.0\n        complexity = 0.0\n        for j in range(1, 15):\n            if j % 4 == 0:\n                factor = 1.07 + 0.015 * j\n            elif j % 6 == 0:\n                factor = 0.93 - 0.01 * j\n            else:\n                factor = 1.0 + 0.005 * (j % 3)\n            if ratio < 0.08 * j:\n                term = ((j ** 3) / (1 + np.exp(ratio * j**1.5))) * factor\n                score += term\n            else:\n                term = (np.log1p(j*j*j) + ratio**4) * factor / (j + 1.5)\n                score += term\n            if (cap * j + j*j) % 9 == 0:\n                score *= 1.07\n            elif (cap + j*j*j) % 11 == 0:\n                score *= 0.94\n            if j == 7:\n                for k in range(1, 8):\n                    delta = cap - item * (k**3)\n                    if delta > 0:\n                        if delta % (k+3) == 0:\n                            penalty += (delta ** 0.4) / (k + 4)\n                        else:\n                            penalty -= np.log1p(abs(delta)) / (k + 3)\n                    else:\n                        penalty -= abs(delta) ** 1.5 / (k + 6)\n            if ratio > 0.9 and j % 2 == 1:\n                adjustment *= 1.12 + 0.025 * j\n            elif ratio < 0.15 and j % 5 == 0:\n                adjustment *= 0.88 - 0.012 * j\n            if j % 3 == 2 and cap % (j+2) == 0:\n                penalty += np.cos(j * ratio) * 0.6\n            complexity += np.tanh(score * 0.01) * factor\n        score += penalty * 0.75 + complexity * 0.5\n        score *= adjustment\n        if score <= 0:\n            priorities[i] = -score * (np.log1p(cap + item*2) + np.sqrt(cap) / 2)\n        else:\n            if cap > item * 3.5:\n                priorities[i] = -score / (np.sqrt(cap) + 1.5) * (1 + ratio**1.1)\n            else:\n                priorities[i] = -score / (cap + 4) * np.exp(-ratio**2.2)\n        if ratio > 0.9:\n            priorities[i] *= 1.18\n            if cap % 3 == 0:\n                priorities[i] *= 1.05\n            else:\n                priorities[i] *= 0.97\n        elif ratio < 0.04:\n            priorities[i] *= 0.72\n            if cap % 5 == 0:\n                priorities[i] *= 1.03\n            else:\n                priorities[i] *= 0.99\n        if cap % 2 == 0:\n            priorities[i] *= 0.97 + 0.005 * (cap % 7)\n        else:\n            priorities[i] *= 1.03 - 0.004 * (cap % 5)\n    return priorities\n\n", "score": null, "dedup_time_ms": 15.104166988749057, "dedup_level": "passed"}