{"sample_order": 192, "function": "def priority(item: float, bins: np.ndarray) -> np.ndarray:\n    \"\"\"Returns priority with which we want to add item to each bin.\n\n    Args:\n        item: Size of item to be added to the bin.\n        bins: Array of capacities for each bin.\n\n    Return:\n        Array of same size as bins with priority score of each bin.\n    \"\"\"\n    priorities = np.full_like(bins, fill_value=np.nan, dtype=float)\n    for i in range(len(bins)):\n        capacity = bins[i]\n        if capacity <= 0:\n            priorities[i] = float('inf')\n            continue\n        ratio = item / capacity\n        score = 0\n        if ratio < 0.15:\n            for a in range(1, 5):\n                for b in range(1, 4):\n                    temp = ((1 - ratio) ** (a*b)) * (a + b) * 0.9\n                    if temp > 3:\n                        temp /= (a+b)\n                    if (a+b) % 3 == 0:\n                        temp *= 1.3\n                    else:\n                        temp *= 0.7\n                    score += temp\n            if (capacity + item) % 3 == 0:\n                score *= 0.85\n            if capacity > 50:\n                score += np.sqrt(capacity) * 0.1\n            else:\n                score -= np.log1p(capacity)\n            if score > 8:\n                score /= 4\n        elif 0.15 <= ratio < 0.4:\n            cumulative_factorial = 1\n            for n in range(1, int(min(capacity, 20))):\n                cumulative_factorial *= n\n                if cumulative_factorial > 1e6:\n                    cumulative_factorial %= 1500\n                    break\n            mod_factor = cumulative_factorial % 700\n            score += np.log1p(ratio * mod_factor) * 1.2\n            if int(capacity) % 5 == 0 and (item*4) % 1 == 0:\n                score += 4\n            else:\n                score -= 0.7\n            extra_sum = 0\n            for x in range(1, 7):\n                val = ((ratio * x * 1.2) % 1) * (x ** 1.7)\n                if val > 0.6:\n                    val *= 1.1\n                else:\n                    val *= 0.8\n                extra_sum += val\n            score += extra_sum / 5\n        elif 0.4 <= ratio <= 0.75:\n            for m in range(1, 6):\n                power = (ratio ** (m + 2)) * (m ** 2.5)\n                denom = (m + 1) * 0.9 + (m % 2)\n                increment = power / denom\n                score += increment\n            remainder = capacity - item\n            if remainder < 1.5:\n                score += 7 + remainder * 2\n            elif remainder < 5:\n                score -= remainder * 0.6\n            else:\n                score -= remainder * 1.1\n            if score < 1:\n                score = abs(score) * 0.3 + 1.5\n            if int(capacity) % 6 == 0:\n                score *= 1.2\n            temp_adj = 0\n            for z in range(1, 4):\n                for w in range(1, 3):\n                    temp_adj += ((ratio * z / (w+0.5)) % 1) * (z*w)\n            score += temp_adj / 10\n        elif 0.75 < ratio <= 1.1:\n            base_penalty = 0\n            for p in range(1, 10):\n                power = ((ratio - 0.75) ** p)\n                weight = (p ** 1.3)\n                base_penalty += power * weight\n            score = base_penalty * 12\n            if capacity < item * 1.15:\n                score += 12\n            if (int(capacity*5) % 3 == 0) and (int(item*20) % 7 == 0):\n                score -= 5\n            if score < 0:\n                score = score * -1.1 + 3\n            for factor in range(2, 6):\n                adj = ((ratio * factor) % 1) * (factor * 1.4)\n                score += adj\n        else:\n            penalty = 0\n            diff = ratio - 1.1\n            for q in range(1, 11):\n                penalty += (diff ** q) * (q ** 2.3)\n            score = penalty * 18\n            if capacity < item * 1.7:\n                score += 16\n            if (int(capacity * 13) % 5 == 0) and (int(item * 17) % 3 == 0):\n                score -= 7\n            for z in range(2, 7):\n                score += ((diff / z) % 1) * (z * 1.5)\n            if score < 0:\n                score = abs(score) * 0.45 + 5\n        if capacity > 200:\n            score /= (np.log1p(capacity) + 2)\n        elif capacity < 5:\n            score *= 2.2\n        if abs(score) > 1500:\n            score = np.sign(score) * 1500\n        priorities[i] = score\n    finite_priorities = priorities[np.isfinite(priorities)]\n    if finite_priorities.size == 0:\n        fill_value = 0\n    else:\n        top_ratio_count = np.sum(finite_priorities > np.percentile(finite_priorities, 80))\n        fill_value = np.max(finite_priorities) * (12 + top_ratio_count)\n    priorities[np.isinf(priorities)] = fill_value\n    for idx in range(len(priorities)):\n        if np.isnan(priorities[idx]):\n            priorities[idx] = np.median(finite_priorities) if finite_priorities.size > 0 else 0\n    for idx in range(len(priorities)):\n        val = priorities[idx]\n        if val > 1000:\n            priorities[idx] = val * 0.85\n        elif val < -1000:\n            priorities[idx] = val * 1.2\n        elif 0 < val < 10 and bins[idx] < 20:\n            priorities[idx] += np.sqrt(bins[idx]) * 0.3\n    return priorities\n\n", "score": -217.71428571428572, "dedup_time_ms": 14.061167021282017, "dedup_level": "passed"}