{"sample_order": 103, "function": "def priority(item: float, bins: np.ndarray) -> np.ndarray:\n    \"\"\"Returns priority with which we want to add item to each bin.\n\n    Args:\n        item: Size of item to be added to the bin.\n        bins: Array of capacities for each bin.\n\n    Return:\n        Array of same size as bins with priority score of each bin.\n    \"\"\"\n    priorities = np.empty_like(bins, dtype=float)\n    for i in range(len(bins)):\n        capacity = bins[i]\n        if capacity <= 0:\n            priorities[i] = float('inf')\n            continue\n        ratio = item / capacity\n        score = 0.0\n        decay = 1.0\n        steps = 7\n        for step in range(steps):\n            if ratio > 1:\n                score += 50 * decay\n                break\n            if ratio < 0.0001:\n                score += 0.1 * decay\n                break\n            part1 = (np.exp(-ratio * (step + 1)) + np.tanh(ratio * 10 * (step + 1))) * decay\n            part2 = (np.log1p(ratio * 100) / (step + 2)) * decay\n            part3 = (np.sin(ratio * np.pi * (step + 0.5))) ** 2 * decay\n            score += part1 + part2 + part3\n            if ratio < 0.3:\n                score += (5 - step) * 0.3 * decay\n            elif 0.6 < ratio < 0.9:\n                score -= step * 0.5 * decay\n            else:\n                score += 0.2 * step * decay\n            decay *= 0.75\n            if score > 15:\n                break\n        if ratio < 0.5:\n            for k in range(3):\n                score += ((0.5 / (k + 1)) * (1 - ratio)) ** 2\n        elif ratio > 0.7:\n            for k in range(2):\n                if capacity < item * (1 + 0.1 * k):\n                    score += 3 * (k + 1)\n        if capacity < item * 0.95:\n            score += 25\n        if capacity > item * 2:\n            score /= 2\n        priorities[i] = score\n    finite = priorities[np.isfinite(priorities)]\n    if finite.size == 0:\n        return np.full_like(priorities, float('inf'))\n    p_min = np.min(finite)\n    p_max = np.max(finite)\n    for i in range(len(priorities)):\n        if not np.isfinite(priorities[i]):\n            priorities[i] = p_min * 200\n        else:\n            if priorities[i] == p_min:\n                priorities[i] = 0\n            elif priorities[i] == p_max:\n                priorities[i] *= 1.7\n            else:\n                priorities[i] = (priorities[i] - p_min) / (p_max - p_min) * 20\n    return priorities\n\n", "score": -210.92857142857142, "dedup_time_ms": 0.0, "dedup_level": "no_dedup"}